sumo_rl/__init__.py
sumo_rl/agents/__init__.py
sumo_rl/agents/ql_agent.py
sumo_rl/environment/__init__.py
sumo_rl/environment/env.py
sumo_rl/environment/observations.py
sumo_rl/environment/resco_envs.py
sumo_rl/environment/traffic_signal.py
sumo_rl/exploration/__init__.py
sumo_rl/exploration/epsilon_greedy.py
sumo_rl/exploration/plot_epsilon.py
sumo_rl/nets/__init__.py
sumo_rl/nets/2way-single-intersection/single-intersection-gen.rou.xml
sumo_rl/nets/2way-single-intersection/single-intersection-horizontal.rou.xml
sumo_rl/nets/2way-single-intersection/single-intersection-vertical.rou.xml
sumo_rl/nets/2way-single-intersection/single-intersection-vhvh.rou.xml
sumo_rl/nets/2way-single-intersection/single-intersection.edg.xml
sumo_rl/nets/2way-single-intersection/single-intersection.net.xml
sumo_rl/nets/2way-single-intersection/single-intersection.nod.xml
sumo_rl/nets/2way-single-intersection/single-intersection.sumocfg
sumo_rl/nets/2x2grid/2x2.net.xml
sumo_rl/nets/2x2grid/2x2.rou.xml
sumo_rl/nets/3x3grid/3x3Grid2lanes.net.xml
sumo_rl/nets/3x3grid/3x3grid.sumocfg
sumo_rl/nets/3x3grid/routes14000.rou.xml
sumo_rl/nets/4x4-Lucas/4x4.edg.xml
sumo_rl/nets/4x4-Lucas/4x4.net.xml
sumo_rl/nets/4x4-Lucas/4x4.nod.xml
sumo_rl/nets/4x4-Lucas/4x4.sumocfg
sumo_rl/nets/4x4-Lucas/4x4c1.rou.xml
sumo_rl/nets/4x4-Lucas/4x4c1c2.rou.xml
sumo_rl/nets/4x4-Lucas/4x4c1c2c1c2.rou.xml
sumo_rl/nets/4x4-Lucas/4x4c2.rou.xml
sumo_rl/nets/4x4-Lucas/4x4c2c1.rou.xml
sumo_rl/nets/4x4-Lucas/4x4teste.rou.xml
sumo_rl/nets/4x4-Lucas/metrics/result_plot.py
sumo_rl/nets/4x4loop/4x4loop.edg.xml
sumo_rl/nets/4x4loop/4x4loop.net.xml
sumo_rl/nets/4x4loop/4x4loop.nod.xml
sumo_rl/nets/4x4loop/4x4loop.rou.xml
sumo_rl/nets/4x4loop/4x4loop.sumocfg
sumo_rl/nets/4x4loop/circle.add.xml
sumo_rl/nets/4x4loop/output_sumo.xml
sumo_rl/nets/Nguyen/nguyen.edg.xml
sumo_rl/nets/Nguyen/nguyen.flows.xml
sumo_rl/nets/Nguyen/nguyen.nod.xml
sumo_rl/nets/Nguyen/nguyen.sumocfg
sumo_rl/nets/Nguyen/nguyen.taz.xml
sumo_rl-1.4.5.dist-info/LICENSE
sumo_rl-1.4.5.dist-info/METADATA
sumo_rl-1.4.5.dist-info/WHEEL
sumo_rl-1.4.5.dist-info/top_level.txt
sumo_rl-1.4.5.dist-info/RECORD
