Metadata-Version: 2.1
Name: sumo-rl
Version: 1.4.5
Summary: RL environments and learning code for traffic signal control in SUMO.
Author-email: Lucas Alegre <lucasnale@gmail.com>
License: MIT License
Project-URL: Homepage, https://lucasalegre.github.io/sumo-rl
Project-URL: Repository, https://github.com/LucasAlegre/sumo-rl
Project-URL: Documentation, https://lucasalegre.github.io/sumo-rl
Project-URL: Bug Report, https://github.com/LucasAlegre/sumo-rl/issues
Keywords: Reinforcement Learning,Traffic Signal Control,SUMO,RL,PettingZoo,gymnasium
Requires-Python: >=3.7
License-File: LICENSE
Requires-Dist: gymnasium >=0.26
Requires-Dist: pettingzoo >=1.22.2
Requires-Dist: numpy
Requires-Dist: pandas
Requires-Dist: pillow
Requires-Dist: sumolib >=1.14.0
Requires-Dist: traci >=1.14.0
Provides-Extra: all
Requires-Dist: pyvirtualdisplay ; extra == 'all'
Provides-Extra: rendering
Requires-Dist: pyvirtualdisplay ; extra == 'rendering'
Provides-Extra: testing
Requires-Dist: pytest ==7.1.3 ; extra == 'testing'
